{
    "bloc_voter_props": {
        "H": [
            0.44062579425388115,
            0.4325412008988607,
            0.42988204049851964,
            0.19597566944175634,
            0.21182441270675864,
            0.48179727523111704,
            0.4531722014175563,
            0.32103715370570635,
            949642.0,
            753514.0
        ],
        "NH": [
            0.5593742057461188,
            0.5674587991011393,
            0.5701179595014804,
            0.8040243305582436,
            0.7881755872932413,
            0.518202724768883,
            0.5468277985824437,
            0.6789628462942936,
            2000197.0,
            2197392.0
        ]
    },
    "cohesion_parameters": {
        "H": {
            "H": 0.77,
            "NH": 0.23
        },
        "NH": {
            "H": 0.52,
            "NH": 0.48
        }
    },
    "alphas": {
        "H": {
            "H": 1,
            "NH": 1
        },
        "NH": {
            "H": 1,
            "NH": 1
        }
    },
    "slate_to_candidates": {
        "H": [
            "H1",
            "H2",
            "H3",
            "H4",
            "H5"
        ],
        "NH": [
            "NH1",
            "NH2",
            "NH3",
            "NH4",
            "NH5"
        ]
    }
}