{
    "bloc_voter_props": {
        "H": [
            0.30527587138917606,
            0.46017602934717494,
            0.5074537472789044,
            0.5083627791379087,
            0.22575497918059434,
            0.1991460050705949,
            0.29795010082328616,
            0.35702516056193706,
            865334.0,
            1159769.0
        ],
        "NH": [
            0.6947241286108239,
            0.5398239706528251,
            0.4925462527210956,
            0.4916372208620913,
            0.7742450208194056,
            0.8008539949294051,
            0.7020498991767139,
            0.6429748394380629,
            2195074.0,
            1776966.0
        ]
    },
    "cohesion_parameters": {
        "H": {
            "H": 0.77,
            "NH": 0.23
        },
        "NH": {
            "H": 0.52,
            "NH": 0.48
        }
    },
    "alphas": {
        "H": {
            "H": 1,
            "NH": 1
        },
        "NH": {
            "H": 1,
            "NH": 1
        }
    },
    "slate_to_candidates": {
        "H": [
            "H1",
            "H2",
            "H3",
            "H4",
            "H5"
        ],
        "NH": [
            "NH1",
            "NH2",
            "NH3",
            "NH4",
            "NH5"
        ]
    }
}